twitchplays_retroarch/__init__.py
twitchplays_retroarch/__main__.py
twitchplays_retroarch/controls_converter.py
twitchplays_retroarch/util.py
twitchplays_retroarch-0.7.0.dist-info/LICENSE
twitchplays_retroarch-0.7.0.dist-info/METADATA
twitchplays_retroarch-0.7.0.dist-info/WHEEL
twitchplays_retroarch-0.7.0.dist-info/entry_points.txt
twitchplays_retroarch-0.7.0.dist-info/top_level.txt
twitchplays_retroarch-0.7.0.dist-info/RECORD
